CONTRIBUTING.rst
LICENSE.txt
MANIFEST.in
README.rst
setup.cfg
setup.py
django_timepiece.egg-info/PKG-INFO
django_timepiece.egg-info/SOURCES.txt
django_timepiece.egg-info/dependency_links.txt
django_timepiece.egg-info/not-zip-safe
django_timepiece.egg-info/requires.txt
django_timepiece.egg-info/top_level.txt
requirements/base.txt
requirements/docs.txt
requirements/tests.txt
timepiece/__init__.py
timepiece/admin.py
timepiece/context_processors.py
timepiece/defaults.py
timepiece/fields.py
timepiece/forms.py
timepiece/models.py
timepiece/urls.py
timepiece/contracts/__init__.py
timepiece/contracts/admin.py
timepiece/contracts/forms.py
timepiece/contracts/models.py
timepiece/contracts/urls.py
timepiece/contracts/views.py
timepiece/contracts/migrations/0001_initial.py
timepiece/contracts/migrations/0002_auto_20150115_1654.py
timepiece/contracts/migrations/0003_auto_20151119_0906.py
timepiece/contracts/migrations/__init__.py
timepiece/contracts/tests/__init__.py
timepiece/contracts/tests/test_contracts.py
timepiece/contracts/tests/test_invoices.py
timepiece/crm/__init__.py
timepiece/crm/admin.py
timepiece/crm/forms.py
timepiece/crm/lookups.py
timepiece/crm/models.py
timepiece/crm/urls.py
timepiece/crm/utils.py
timepiece/crm/views.py
timepiece/crm/migrations/0001_initial.py
timepiece/crm/migrations/0002_auto_20150115_1654.py
timepiece/crm/migrations/0003_auto_20151119_0906.py
timepiece/crm/migrations/__init__.py
timepiece/crm/tests/__init__.py
timepiece/crm/tests/test_businesses.py
timepiece/crm/tests/test_project_timesheet.py
timepiece/crm/tests/test_projects.py
timepiece/crm/tests/test_quick_search.py
timepiece/crm/tests/test_relationships.py
timepiece/crm/tests/test_users.py
timepiece/entries/__init__.py
timepiece/entries/admin.py
timepiece/entries/forms.py
timepiece/entries/lookups.py
timepiece/entries/models.py
timepiece/entries/urls.py
timepiece/entries/views.py
timepiece/entries/migrations/0001_initial.py
timepiece/entries/migrations/0002_auto_20151119_0906.py
timepiece/entries/migrations/0003_auto_20151217_1350.py
timepiece/entries/migrations/__init__.py
timepiece/entries/tests/__init__.py
timepiece/entries/tests/test_dashboard.py
timepiece/entries/tests/test_lookups.py
